[
    {
        "speaker": "Host (Jane)",
        "text": "Welcome back to our podcast! Today, we're diving into the world of AI in call centers."
    },
    {
        "speaker": "Guest",
        "text": "Thanks for having me, Jane! It's a fascinating topic."
    },
    {
        "speaker": "Host (Jane)",
        "text": "Absolutely! So, let’s kick things off. What inspired this AI-enhanced call center project?"
    },
    {
        "speaker": "Guest",
        "text": "We wanted to boost efficiency and really enhance customer satisfaction."
    },
    {
        "speaker": "Host (Jane)",
        "text": "That sounds like a game changer! What were some of the bumps in the road early on?"
    },
    {
        "speaker": "Guest",
        "text": "Oh, we faced some serious defect burndown challenges and communication hiccups."
    },
    {
        "speaker": "Host (Jane)",
        "text": "Communication is everything! How did you tackle those issues?"
    },
    {
        "speaker": "Guest",
        "text": "We started daily stand-up meetings to keep everyone on the same page."
    },
    {
        "speaker": "Host (Jane)",
        "text": "Great idea! What about the tech side? Did you run into any major bugs?"
    },
    {
        "speaker": "Guest",
        "text": "Definitely! We had some new feature malfunctions and leftover bugs."
    },
    {
        "speaker": "Host (Jane)",
        "text": "Yikes! How did you prioritize fixing those pesky issues?"
    },
    {
        "speaker": "Guest",
        "text": "We launched an intensive bug-fixing sprint to tackle the critical defects."
    },
    {
        "speaker": "Host (Jane)",
        "text": "Smart move! How did you ensure the team was aligned during all this?"
    },
    {
        "speaker": "Guest",
        "text": "We created a focus group of call center agents to gather their feedback."
    },
    {
        "speaker": "Host (Jane)",
        "text": "That’s a clever approach! What’s the current status of the project?"
    },
    {
        "speaker": "Guest",
        "text": "We're still working on performance under load and bridging some integration gaps."
    },
    {
        "speaker": "Host (Jane)",
        "text": "Sounds challenging! How are you managing those risks?"
    },
    {
        "speaker": "Guest",
        "text": "We formed a targeted task force to focus on fixing the critical defects."
    },
    {
        "speaker": "Host (Jane)",
        "text": "And how's the team coping with the pressure?"
    },
    {
        "speaker": "Guest",
        "text": "We've ramped up engagement with the agents to keep morale high."
    },
    {
        "speaker": "Host (Jane)",
        "text": "That’s so important! What about training for the agents on the new system?"
    },
    {
        "speaker": "Guest",
        "text": "We're developing a comprehensive training program to help them adapt."
    },
    {
        "speaker": "Host (Jane)",
        "text": "Excellent! Any final thoughts on the future of AI in call centers?"
    },
    {
        "speaker": "Guest",
        "text": "AI is set to revolutionize customer service, making it more efficient and personalized."
    },
    {
        "speaker": "Host (Jane)",
        "text": "I can't wait to see how it all evolves! Thanks for sharing your insights, Alex."
    },
    {
        "speaker": "Guest",
        "text": "Thank you, Jane! It was a pleasure to chat."
    },
    {
        "speaker": "Host (Jane)",
        "text": "And thank you to our listeners! Stay tuned for more exciting discussions on tech innovations."
    }
]